[
  {
    "_id": {
      "$oid": "67c7ead44880417f86d6f4db"
    },
    "alert_ID": "2025-03-05 09:10:28",
    "date": "2025-03-05",
    "time": "09:10:28",
    "cam_id": "camera_9",
    "alerts": [
      {
        "candidate": "2",
        "desk": 29,
        "title": "Student Interacting with Invigilator"
      }
    ],
    "file_name": "1741155028.361221"
  },
  {
    "_id": {
      "$oid": "67c82ec64880417f86d6f537"
    },
    "alert_ID": "2025-03-05 14:00:22",
    "date": "2025-03-05",
    "time": "14:00:22",
    "cam_id": "camera_9",
    "alerts": [
      {
        "candidate": "2",
        "desk": 29,
        "title": "Student Interacting with Invigilator"
      }
    ],
    "file_name": "1741172422.2606254"
  },
  {
    "_id": {
      "$oid": "67c82ed74880417f86d6f538"
    },
    "alert_ID": "2025-03-05 14:00:39",
    "date": "2025-03-05",
    "time": "14:00:39",
    "cam_id": "camera_9",
    "alerts": [
      {
        "candidate": "2",
        "desk": 29,
        "title": "Student Interacting with Invigilator"
      }
    ],
    "file_name": "1741172439.4550848"
  },
  {
    "_id": {
      "$oid": "67c834044880417f86d6f54e"
    },
    "alert_ID": "2025-03-05 14:22:44",
    "date": "2025-03-05",
    "time": "14:22:44",
    "cam_id": "camera_9",
    "alerts": [
      {
        "candidate": "2",
        "desk": 29,
        "title": "Student Interacting with Invigilator"
      }
    ],
    "file_name": "1741173764.5570967"
  },
  {
    "_id": {
      "$oid": "67c8340b4880417f86d6f54f"
    },
    "alert_ID": "2025-03-05 14:22:51",
    "date": "2025-03-05",
    "time": "14:22:51",
    "cam_id": "camera_9",
    "alerts": [
      {
        "candidate": "2",
        "desk": 29,
        "title": "Student Interacting with Invigilator"
      }
    ],
    "file_name": "1741173771.325152"
  },
  {
    "_id": {
      "$oid": "67c834104880417f86d6f550"
    },
    "alert_ID": "2025-03-05 14:22:56",
    "date": "2025-03-05",
    "time": "14:22:56",
    "cam_id": "camera_9",
    "alerts": [
      {
        "candidate": "2",
        "desk": 29,
        "title": "Student Interacting with Invigilator"
      }
    ],
    "file_name": "1741173776.0104396"
  }
]