[
  {
    "_id": {
      "$oid": "67b1d7b8b365de89cafba2ab"
    },
    "alert_ID": "2025-02-16 15:19:04",
    "date": "2025-02-16",
    "time": "15:19:04",
    "cam_id": "camera_9",
    "alerts": [
      {
        "candidate": "2",
        "desk": 29,
        "title": "Using Mobile Phone"
      }
    ],
    "file_name": "1739708344.9235961"
  },
  {
    "_id": {
      "$oid": "67b1d7c4b365de89cafba2ac"
    },
    "alert_ID": "2025-02-16 15:19:16",
    "date": "2025-02-16",
    "time": "15:19:16",
    "cam_id": "camera_9",
    "alerts": [
      {
        "candidate": "2",
        "desk": 29,
        "title": "Using Mobile Phone"
      }
    ],
    "file_name": "1739708356.4655008"
  },
  {
    "_id": {
      "$oid": "67b1d7ceb365de89cafba2ad"
    },
    "alert_ID": "2025-02-16 15:19:26",
    "date": "2025-02-16",
    "time": "15:19:26",
    "cam_id": "camera_9",
    "alerts": [
      {
        "candidate": "2",
        "desk": 29,
        "title": "Using Mobile Phone"
      }
    ],
    "file_name": "1739708366.5625515"
  },
  {
    "_id": {
      "$oid": "67b1d7d9b365de89cafba2ae"
    },
    "alert_ID": "2025-02-16 15:19:37",
    "date": "2025-02-16",
    "time": "15:19:37",
    "cam_id": "camera_9",
    "alerts": [
      {
        "candidate": "2",
        "desk": 29,
        "title": "Using Mobile Phone"
      }
    ],
    "file_name": "1739708377.0946655"
  },
  {
    "_id": {
      "$oid": "67b1d7ddb365de89cafba2af"
    },
    "alert_ID": "2025-02-16 15:19:41",
    "date": "2025-02-16",
    "time": "15:19:41",
    "cam_id": "camera_9",
    "alerts": [
      {
        "candidate": "2",
        "desk": 29,
        "title": "Using Mobile Phone"
      }
    ],
    "file_name": "1739708381.616769"
  }
]