[
  {
    "_id": {
      "$oid": "67aad136aec15695835dd14c"
    },
    "alert_ID": "2025-02-11 07:25:26",
    "date": "2025-02-11",
    "time": "07:25:26",
    "cam_id": "camera_1",
    "alerts": [
      {
        "candidate": "2",
        "desk": 2,
        "title": "Student Interacting with Invigilator"
      }
    ],
    "file_name": "1739247926.1578896"
  },
  {
    "_id": {
      "$oid": "67aad13daec15695835dd14d"
    },
    "alert_ID": "2025-02-11 07:25:33",
    "date": "2025-02-11",
    "time": "07:25:33",
    "cam_id": "camera_1",
    "alerts": [
      {
        "candidate": "2",
        "desk": 2,
        "title": "Student Interacting with Invigilator"
      }
    ],
    "file_name": "1739247933.1588485"
  },
  {
    "_id": {
      "$oid": "67aad153aec15695835dd14e"
    },
    "alert_ID": "2025-02-11 07:25:55",
    "date": "2025-02-11",
    "time": "07:25:55",
    "cam_id": "camera_1",
    "alerts": [
      {
        "candidate": "2",
        "desk": 2,
        "title": "Student Interacting with Invigilator"
      }
    ],
    "file_name": "1739247955.5893803"
  },
  {
    "_id": {
      "$oid": "67aad157aec15695835dd14f"
    },
    "alert_ID": "2025-02-11 07:25:59",
    "date": "2025-02-11",
    "time": "07:25:59",
    "cam_id": "camera_1",
    "alerts": [
      {
        "candidate": "2",
        "desk": 2,
        "title": "Student Interacting with Invigilator"
      }
    ],
    "file_name": "1739247959.9794977"
  },
  {
    "_id": {
      "$oid": "67aad1e2aec15695835dd155"
    },
    "alert_ID": "2025-02-11 07:28:18",
    "date": "2025-02-11",
    "time": "07:28:18",
    "cam_id": "camera_1",
    "alerts": [
      {
        "candidate": "2",
        "desk": 2,
        "title": "Student Interacting with Invigilator"
      }
    ],
    "file_name": "1739248098.539784"
  },
  {
    "_id": {
      "$oid": "67aae82caec15695835dd17a"
    },
    "alert_ID": "2025-02-11 09:03:24",
    "date": "2025-02-11",
    "time": "09:03:24",
    "cam_id": "camera_1",
    "alerts": [
      {
        "candidate": "2",
        "desk": 2,
        "title": "Student Interacting with Invigilator"
      }
    ],
    "file_name": "1739253804.6634996"
  },
  {
    "_id": {
      "$oid": "67aaf5bdaec15695835dd19b"
    },
    "alert_ID": "2025-02-11 10:01:17",
    "date": "2025-02-11",
    "time": "10:01:17",
    "cam_id": "camera_1",
    "alerts": [
      {
        "candidate": "2",
        "desk": 2,
        "title": "Student Interacting with Invigilator"
      }
    ],
    "file_name": "1739257277.4447565"
  },
  {
    "_id": {
      "$oid": "67ab4cdcb862a9c108044f06"
    },
    "alert_ID": "2025-02-11 16:13:00",
    "date": "2025-02-11",
    "time": "16:13:00",
    "cam_id": "camera_1",
    "alerts": [
      {
        "candidate": "2",
        "desk": 2,
        "title": "Student Interacting with Invigilator"
      }
    ],
    "file_name": "1739279580.8106303"
  },
  {
    "_id": {
      "$oid": "67ab5658b862a9c108044f4c"
    },
    "alert_ID": "2025-02-11 16:53:28",
    "date": "2025-02-11",
    "time": "16:53:28",
    "cam_id": "camera_1",
    "alerts": [
      {
        "candidate": "2",
        "desk": 2,
        "title": "Student Interacting with Invigilator"
      }
    ],
    "file_name": "1739282008.9631221"
  },
  {
    "_id": {
      "$oid": "67ab7d61b862a9c108045316"
    },
    "alert_ID": "2025-02-11 19:40:01",
    "date": "2025-02-11",
    "time": "19:40:01",
    "cam_id": "camera_1",
    "alerts": [
      {
        "candidate": "2",
        "desk": 2,
        "title": "Student Interacting with Invigilator"
      }
    ],
    "file_name": "1739292001.4065883"
  },
  {
    "_id": {
      "$oid": "67ab890db862a9c108045350"
    },
    "alert_ID": "2025-02-11 20:29:49",
    "date": "2025-02-11",
    "time": "20:29:49",
    "cam_id": "camera_1",
    "alerts": [
      {
        "candidate": "2",
        "desk": 2,
        "title": "Student Interacting with Invigilator"
      }
    ],
    "file_name": "1739294989.3267338"
  },
  {
    "_id": {
      "$oid": "67ab891db862a9c108045351"
    },
    "alert_ID": "2025-02-11 20:30:05",
    "date": "2025-02-11",
    "time": "20:30:05",
    "cam_id": "camera_1",
    "alerts": [
      {
        "candidate": "2",
        "desk": 2,
        "title": "Student Interacting with Invigilator"
      }
    ],
    "file_name": "1739295005.7104387"
  }
]