[
  {
    "_id": {
      "$oid": "67c3f6cc968565b0ae06b165"
    },
    "alert_ID": "2025-03-02 09:12:28",
    "date": "2025-03-02",
    "time": "09:12:28",
    "cam_id": "camera_5",
    "alerts": [
      {
        "candidate": "4",
        "desk": 16,
        "title": "Looking Around"
      }
    ],
    "file_name": "1740895948.4083652"
  },
  {
    "_id": {
      "$oid": "67c454854880417f86d6f3f2"
    },
    "alert_ID": "2025-03-02 15:52:21",
    "date": "2025-03-02",
    "time": "15:52:21",
    "cam_id": "camera_5",
    "alerts": [
      {
        "candidate": "4",
        "desk": 16,
        "title": "Looking Around"
      }
    ],
    "file_name": "1740919941.7081628"
  }
]